{"home":{"title":"vinh","me":{"title":"Hello.","content":"My name is <i><b>vinh</b></i>, I'm a programmer. This is my corner on the Internet. I mostly write about technology related stuffs, my family, some time I also mention my trust in Jesus Christ, my Savior."},"journey":{"title":"journey","years":[{"year":2020,"events":["started this site."]}]},"work":{"title":"companies","years":[{"year":2022,"events":["mesoneer"]},{"year":2021,"events":["UMB"]},{"year":2018,"events":["ubitec"]},{"year":2013,"events":["Axon Active Vietnam"]}]}},"site":{"title":"Sài Gòn giãn cách xã hội","path":"/blog/entry/2021/07/09/2nd-social-distancing-in-saigon"},"blog":{"entries":[],"entriesByTag":[],"entry":{"title":"Sài Gòn giãn cách xã hội","url":"/blog/entry/2021/07/09/2nd-social-distancing-in-saigon","slug":"2nd-social-distancing-in-saigon","author":"vinh","preview":"Lần đầu tiên Sài Gòn thật sự đối mặt với đại dịch COVID-19.","created":"2021-07-09T06:24:33.174Z","updated":"2021-07-09T06:24:33.174Z","content":"<p>Nay là ngày đầu Sài Gòn giãn cách xã hội, mình ghi lại tình trạng hiện tại để\nsau này nhìn lại.</p>\n<ul>\n<li>Mọi người mua đồ dự trữ nhiều hơn vài lần so với Tết.</li>\n<li>Cửa hàng tiện lợi, siêu thị thường xuyên hết hàng.</li>\n<li>Ngoài siêu thị, tiệm tạp hóa, những cửa hàng khác dừng hoạt động, kể cả\nGrabbike, cửa hàng take away.</li>\n<li>Đi lại phải có lý do chính đáng, nếu không có thể bị phạt, vẫn chưa hiểu cơ\nchế kiểm soát thế nào.</li>\n<li>Thành phố nhận thêm 700k liều vaccine.</li>\n<li>Người từ bên ngoài vẫn vào được thành phố nếu có xét nghiệm âm tính.</li>\n</ul>\n<p>Dự đoán của mình.</p>\n<ul>\n<li>Thành phố sẽ cố gắng có thêm nhiều vaccine.</li>\n<li>Tình trạng giãn cách có thể kéo dài nếu vaccine không được tiêm trên diện\nrộng.</li>\n<li>Mua hàng ở siêu thị có nguy cơ lây nhiễm cao do tập trung đông trong không\ngian kín.</li>\n</ul>\n<p>Mình đang ở ngoài Sài Gòn, mà giờ muốn vô cũng không được.</p>\n<p><a href=\"2nd-social-distancing-in-saigon/image/out_of_sg.jpg\"><img src=\"./2nd-social-distancing-in-saigon/image/out_of_sg_small.jpg\" alt=\"A small town near Saigon\" title=\"A small town near Saigon\" class=\"blog-entry__image\" /></a></p>\n","tags":["covid-19","life","saigon"]}}}