[{"title":"Đừng dùng lại mật khẩu, hãy dùng PASSWORD MANAGER!","url":"/blog/entry/2019/05/25/dung-dung-lai-mat-khau-hay-dung-password-manager","slug":"dung-dung-lai-mat-khau-hay-dung-password-manager","author":"vinh","preview":"Ai trong chúng ta hẳn đã có không dưới 5 tài khoản Internet: Internet Banking, Facebook, Zalo, Viber, Gmail.. Và mật khẩu là thành phần quan trọng giúp bảo vệ các tài khoản này.","created":"2019-05-25T17:00:00.000Z","updated":"2019-05-25T17:00:00.000Z","tags":["password-manager","privacy","software"]},{"title":"Arch Linux - Nếu một ngày không có Windows","url":"/blog/entry/2017/05/28/archlinux-neu-mot-ngay-khong-co-windows","slug":"archlinux-neu-mot-ngay-khong-co-windows","author":"vinh","preview":"Cái giả thuyết Windows ngày nào đó sẽ biến mất thật xa vời, nhưng ít ra, tôi đã không dùng nó từ 2 năm nay, công việc cũng như cá nhân.","created":"2017-05-28T17:00:00.000Z","updated":"2017-05-28T17:00:00.000Z","tags":["gui","linux","privacy","unix"]}]