{"title":"Tạo Dynamic Web Project (Eclipse 3.5) từ source-code có sẵn.","url":"/blog/entry/2011/10/07/tao-dynamic-web-project-eclipse","slug":"tao-dynamic-web-project-eclipse","author":"vinh","preview":"Vì vài lý do tui sao lưu source-code và xóa meta-data của Eclipse Project, hậu quả hôm nay import lại project phát hiện không thể convert từ Java Project sang Dynamic Web Project.","created":"2011-10-07T17:00:00.000Z","updated":"2011-10-07T17:00:00.000Z","content":"<p>Vì vài lý do tui sao lưu <em>source-code</em> và xóa <em>meta-data</em> của Eclipse Project,\nhậu quả hôm nay <em>import</em> lại <em>project</em> phát hiện không thể <em>convert</em> từ Java\nProject sang Dynamic Web Project.</p>\n<p>Chuyện cũng không lớn lắm</p>\n<ul>\n<li>Trước hết bạn tạo <em>project</em> mới trùng với tên <em>project</em> muốn <em>import</em> (ví dụ:\nExample).</li>\n<li>Mở trình quản lý tập tin bạn thường dùng, chuyển tới thư mục chứa <em>project</em>\nmới tạo. <em>Copy</em> thư mục .settings, tập tin .classpath và .project vào thư mục\nchứa project của bạn.</li>\n<li>Xóa project bạn vừa tạo.</li>\n<li>Vào Eclipse chọn File &gt; Import.. &gt; Existing Projects into Workspace, chọn\nNext.</li>\n<li>Tại mục Select root directory, chọn thư mục chứa project của bạn.</li>\n<li><em>Project</em> của bạn sẽ hiện ra tại mục Projects, <em>check</em> vào nó và chọn Finish.</li>\n</ul>\n","tags":["eclipse"]}